{
  "400001": "not sexist",
  "400002": "not sexist",
  "400003": "sexist",
  "400004": "not sexist",
  "400005": "not sexist",
  "400006": "not sexist",
  "400007": "not sexist",
  "400009": "sexist",
  "400012": "sexist",
  "400015": "not sexist",
  "400017": "not sexist",
  "400020": "sexist",
  "400021": "sexist",
  "400022": "not sexist",
  "400023": "not sexist",
  "400024": "not sexist",
  "400025": "not sexist",
  "400026": "not sexist",
  "400027": "not sexist",
  "400028": "sexist",
  "400031": "sexist",
  "400032": "not sexist",
  "400033": "not sexist",
  "400034": "sexist",
  "400035": "not sexist",
  "400036": "not sexist",
  "400037": "sexist",
  "400040": "sexist",
  "400041": "not sexist",
  "400042": "not sexist",
  "400044": "not sexist",
  "400045": "sexist",
  "400046": "sexist",
  "400047": "not sexist",
  "400048": "not sexist",
  "400049": "not sexist",
  "400050": "not sexist",
  "400051": "not sexist",
  "400052": "not sexist",
  "400053": "not sexist",
  "400055": "not sexist",
  "400056": "not sexist",
  "400057": "not sexist",
  "400058": "not sexist",
  "400059": "sexist",
  "400060": "not sexist",
  "400061": "not sexist",
  "400062": "sexist",
  "400064": "not sexist",
  "400065": "not sexist",
  "400067": "sexist",
  "400069": "not sexist",
  "400070": "not sexist",
  "400071": "not sexist",
  "400072": "not sexist",
  "400074": "not sexist",
  "400075": "not sexist",
  "400076": "sexist",
  "400077": "sexist",
  "400078": "sexist",
  "400080": "sexist",
  "400081": "sexist",
  "400082": "sexist",
  "400083": "not sexist",
  "400084": "not sexist",
  "400085": "not sexist",
  "400086": "not sexist",
  "400087": "not sexist",
  "400088": "not sexist",
  "400089": "not sexist",
  "400090": "not sexist",
  "400091": "not sexist",
  "400092": "not sexist",
  "400093": "sexist",
  "400094": "sexist",
  "400095": "sexist",
  "400096": "not sexist",
  "400097": "sexist",
  "400098": "sexist",
  "400100": "not sexist",
  "400101": "not sexist",
  "400102": "sexist",
  "400103": "not sexist",
  "400104": "not sexist",
  "400105": "not sexist",
  "400107": "sexist",
  "400108": "sexist",
  "400109": "not sexist",
  "400111": "not sexist",
  "400113": "sexist",
  "400114": "not sexist",
  "400116": "not sexist",
  "400117": "not sexist",
  "400118": "sexist",
  "400121": "not sexist",
  "400122": "not sexist",
  "400123": "not sexist",
  "400124": "sexist",
  "400125": "not sexist",
  "400126": "sexist",
  "400127": "not sexist",
  "400129": "not sexist",
  "400130": "not sexist",
  "400131": "not sexist",
  "400132": "not sexist",
  "400133": "not sexist",
  "400134": "sexist",
  "400135": "not sexist",
  "400136": "not sexist",
  "400137": "not sexist",
  "400138": "sexist",
  "400140": "sexist",
  "400141": "sexist",
  "400142": "not sexist",
  "400143": "not sexist",
  "400144": "sexist",
  "400145": "not sexist",
  "400147": "not sexist",
  "400148": "not sexist",
  "400149": "sexist",
  "400151": "sexist",
  "400152": "sexist",
  "400155": "not sexist",
  "400156": "not sexist",
  "400157": "sexist",
  "400159": "not sexist",
  "400161": "not sexist",
  "400162": "not sexist",
  "400166": "sexist",
  "400169": "sexist",
  "400170": "not sexist",
  "400171": "not sexist",
  "400174": "sexist",
  "400175": "not sexist",
  "400176": "not sexist",
  "400177": "not sexist",
  "400178": "not sexist",
  "400180": "sexist",
  "400181": "not sexist",
  "400182": "not sexist",
  "400183": "not sexist",
  "400184": "not sexist",
  "400185": "sexist",
  "400186": "sexist",
  "400187": "not sexist",
  "400188": "sexist",
  "400189": "not sexist",
  "400190": "sexist",
  "400191": "not sexist",
  "400192": "not sexist",
  "400194": "not sexist",
  "400195": "not sexist",
  "400196": "not sexist",
  "400197": "sexist",
  "400198": "sexist",
  "400199": "not sexist",
  "400200": "sexist",
  "400201": "sexist",
  "400202": "sexist",
  "400203": "sexist",
  "400204": "sexist",
  "400205": "sexist",
  "400206": "sexist",
  "400207": "not sexist",
  "400208": "not sexist",
  "400209": "not sexist",
  "400210": "not sexist",
  "400211": "not sexist",
  "400212": "not sexist",
  "400213": "not sexist",
  "400214": "not sexist",
  "400215": "not sexist",
  "400218": "not sexist",
  "400219": "not sexist",
  "400222": "sexist",
  "400223": "not sexist",
  "400224": "sexist",
  "400225": "not sexist",
  "400226": "sexist",
  "400227": "sexist",
  "400228": "not sexist",
  "400229": "sexist",
  "400230": "not sexist",
  "400232": "not sexist",
  "400233": "not sexist",
  "400234": "not sexist",
  "400235": "sexist",
  "400236": "sexist",
  "400237": "sexist",
  "400238": "sexist",
  "400239": "not sexist",
  "400240": "not sexist",
  "400241": "sexist",
  "400242": "not sexist",
  "400243": "sexist",
  "400245": "not sexist",
  "400246": "sexist",
  "400248": "sexist",
  "400250": "not sexist",
  "400252": "sexist",
  "400255": "not sexist",
  "400256": "not sexist",
  "400257": "sexist",
  "400258": "sexist",
  "400259": "not sexist",
  "400261": "sexist",
  "400262": "not sexist",
  "400263": "not sexist",
  "400264": "not sexist",
  "400265": "not sexist",
  "400266": "not sexist",
  "400267": "not sexist",
  "400268": "not sexist",
  "400269": "sexist",
  "400270": "not sexist",
  "400272": "sexist",
  "400273": "not sexist",
  "400274": "not sexist",
  "400275": "not sexist",
  "400276": "not sexist",
  "400277": "not sexist",
  "400278": "not sexist",
  "400279": "not sexist",
  "400280": "not sexist",
  "400281": "not sexist",
  "400282": "not sexist",
  "400283": "not sexist",
  "400284": "not sexist",
  "400285": "sexist",
  "400286": "sexist",
  "400287": "not sexist",
  "400288": "not sexist",
  "400289": "not sexist",
  "400290": "not sexist",
  "400291": "not sexist",
  "400292": "sexist",
  "400294": "sexist",
  "400295": "sexist",
  "400296": "sexist",
  "400297": "not sexist",
  "400298": "not sexist",
  "400300": "not sexist",
  "400302": "not sexist",
  "400303": "sexist",
  "400304": "sexist",
  "400306": "sexist",
  "400307": "not sexist",
  "400308": "not sexist",
  "400309": "not sexist",
  "400311": "not sexist",
  "400313": "not sexist",
  "400314": "not sexist",
  "400315": "not sexist",
  "400316": "not sexist",
  "400317": "not sexist",
  "400318": "not sexist",
  "400319": "not sexist",
  "400320": "not sexist",
  "400321": "sexist",
  "400323": "not sexist",
  "400324": "not sexist",
  "400325": "not sexist",
  "400326": "not sexist",
  "400327": "not sexist",
  "400328": "sexist",
  "400329": "sexist",
  "400331": "not sexist",
  "400333": "not sexist",
  "400334": "not sexist",
  "400335": "not sexist",
  "400336": "not sexist",
  "400337": "not sexist",
  "400341": "sexist",
  "400343": "sexist",
  "400344": "not sexist",
  "400346": "not sexist",
  "400347": "sexist",
  "400349": "not sexist",
  "400350": "sexist",
  "400351": "not sexist",
  "400353": "not sexist",
  "400354": "not sexist",
  "400355": "not sexist",
  "400356": "not sexist",
  "400357": "not sexist",
  "400358": "sexist",
  "400359": "not sexist",
  "400360": "sexist",
  "400361": "not sexist",
  "400362": "not sexist",
  "400363": "not sexist",
  "400364": "not sexist",
  "400365": "not sexist",
  "400366": "not sexist",
  "400367": "not sexist",
  "400368": "not sexist",
  "400369": "not sexist",
  "400370": "sexist",
  "400372": "sexist",
  "400373": "sexist",
  "400374": "not sexist",
  "400375": "not sexist",
  "400376": "not sexist",
  "400377": "not sexist",
  "400378": "not sexist",
  "400379": "sexist",
  "400380": "sexist",
  "400381": "sexist",
  "400382": "sexist",
  "400383": "sexist",
  "400384": "sexist",
  "400385": "not sexist",
  "400386": "not sexist",
  "400387": "not sexist",
  "400388": "not sexist",
  "400389": "not sexist",
  "400390": "not sexist",
  "400391": "sexist",
  "400394": "not sexist",
  "400395": "not sexist",
  "400396": "not sexist",
  "400397": "not sexist",
  "400398": "not sexist",
  "400400": "not sexist",
  "400401": "not sexist",
  "400402": "not sexist",
  "400403": "sexist",
  "400404": "not sexist",
  "400405": "not sexist",
  "400407": "sexist",
  "400408": "sexist",
  "400409": "sexist",
  "400410": "not sexist",
  "400411": "sexist",
  "400412": "not sexist",
  "400413": "not sexist",
  "400414": "not sexist",
  "400418": "not sexist",
  "400419": "not sexist",
  "400420": "not sexist",
  "400422": "not sexist",
  "400423": "not sexist",
  "400424": "not sexist",
  "400425": "sexist",
  "400426": "sexist",
  "400427": "sexist",
  "400428": "sexist",
  "400429": "sexist",
  "400431": "not sexist",
  "400433": "not sexist",
  "400434": "not sexist",
  "400436": "not sexist",
  "400437": "sexist",
  "400438": "sexist",
  "400440": "sexist",
  "400442": "not sexist",
  "400443": "not sexist",
  "400444": "not sexist",
  "400445": "sexist",
  "400446": "not sexist",
  "400447": "sexist",
  "400448": "not sexist",
  "400449": "sexist",
  "400450": "sexist",
  "400451": "not sexist",
  "400452": "sexist",
  "400453": "not sexist",
  "400455": "not sexist",
  "400456": "sexist",
  "400457": "sexist",
  "400458": "not sexist",
  "400459": "not sexist",
  "400460": "sexist",
  "400461": "sexist",
  "400462": "sexist",
  "400463": "sexist",
  "400464": "sexist",
  "400466": "not sexist",
  "400467": "not sexist",
  "400468": "sexist",
  "400469": "not sexist",
  "400471": "not sexist",
  "400472": "not sexist",
  "400473": "not sexist",
  "400474": "not sexist",
  "400475": "not sexist",
  "400476": "not sexist",
  "400477": "not sexist",
  "400478": "sexist",
  "400479": "not sexist",
  "400480": "not sexist",
  "400481": "not sexist",
  "400482": "sexist",
  "400483": "not sexist",
  "400484": "sexist",
  "400485": "sexist",
  "400486": "sexist",
  "400487": "sexist",
  "400488": "sexist",
  "400489": "sexist"
}